spyderml/__init__.py
spyderml/bin/spyderml
spyderml/main.py
spyderml/src/__init__.py
spyderml/src/asciiarts.py
spyderml/src/detectos.py
spyderml/src/file.py
spyderml/src/handle_headers_and_proxy.py
spyderml/src/spidercrawler.py
spyderml/src/spyder_reqs.py
spyderml/src/utils.py
spyder_ml-2.1.4.dist-info/LICENSE
spyder_ml-2.1.4.dist-info/METADATA
spyder_ml-2.1.4.dist-info/WHEEL
spyder_ml-2.1.4.dist-info/entry_points.txt
spyder_ml-2.1.4.dist-info/RECORD
