Metadata-Version: 2.1
Name: spyder-ml
Version: 2.1.4
Summary: A tool made to facilitate the analysis of html code.
Home-page: https://github.com/accessmaker/Spyder-ml
License: MIT
Author: Lucas dSilva
Author-email: accessmaker.mlbb@gmail.com
Requires-Python: >=3.8,<4.0
Classifier: Development Status :: 5 - Production/Stable
Classifier: License :: OSI Approved :: MIT License
Classifier: Programming Language :: Python :: 3
Classifier: Programming Language :: Python :: 3.8
Classifier: Programming Language :: Python :: 3.9
Classifier: Programming Language :: Python :: 3.10
Classifier: Programming Language :: Python :: 3.11
Requires-Dist: argcomplete (>=2.0.5,<3.0.0)
Requires-Dist: beautifulsoup4 (>=4.11.1,<5.0.0)
Requires-Dist: bs4 (>=0.0.1,<0.0.2)
Requires-Dist: colorama (>=0.4.6,<0.5.0)
Requires-Dist: pysocks (>=1.7.1,<2.0.0)
Requires-Dist: requests (>=2.28.2,<3.0.0)
Requires-Dist: types-requests (>=2.28.11.17,<3.0.0.0)
Requires-Dist: urllib3 (>=1.26.14,<2.0.0)
Requires-Dist: webtech (>=1.3.2,<2.0.0)
Project-URL: Repository, https://github.com/accessmaker/Spyder-ml
